a/__init__.py
a/module.py
b/__init__.py
b/module.py
c/__init__.py
c/module.py
q9-3.1.2.dist-info/DESCRIPTION.rst
q9-3.1.2.dist-info/METADATA
q9-3.1.2.dist-info/RECORD
q9-3.1.2.dist-info/WHEEL
q9-3.1.2.dist-info/metadata.json
q9-3.1.2.dist-info/top_level.txt
