Metadata-Version: 2.0
Name: q9
Version: 3.1.2
Summary: UNKNOWN
Home-page: UNKNOWN
Author: luyendd
Author-email: tudu8603@gmail.com
License: UNKNOWN
Platform: UNKNOWN
Requires-Dist: opencv-python
